img2cmap/__init__.py
img2cmap/convert.py
img2cmap-0.2.3.dist-info/AUTHORS.rst
img2cmap-0.2.3.dist-info/LICENSE
img2cmap-0.2.3.dist-info/METADATA
img2cmap-0.2.3.dist-info/WHEEL
img2cmap-0.2.3.dist-info/top_level.txt
img2cmap-0.2.3.dist-info/RECORD
