Metadata-Version: 2.1
Name: img2cmap
Version: 0.2.3
Summary: Create colormaps from images
Author-email: Kevin Arvai <arvkevi@gmail.com>, Marshall Krassenstein <mpkrass@gmail.com>
License: MIT License        
Project-URL: Homepage, https://github.com/arvkevi/kneed
Project-URL: Bug Tracker, https://github.com/arvkevi/kneed/issues
Keywords: colormap,matplotlib,kmeans,data visualization
Classifier: License :: OSI Approved :: MIT License
Classifier: Development Status :: 2 - Pre-Alpha
Classifier: Operating System :: OS Independent
Classifier: Intended Audience :: Developers
Classifier: Operating System :: Unix
Classifier: Operating System :: POSIX
Classifier: Operating System :: Microsoft :: Windows
Classifier: Operating System :: MacOS
Classifier: Programming Language :: Python
Classifier: Programming Language :: Python :: 3
Classifier: Programming Language :: Python :: 3 :: Only
Classifier: Programming Language :: Python :: 3.7
Classifier: Programming Language :: Python :: 3.8
Classifier: Programming Language :: Python :: 3.9
Classifier: Programming Language :: Python :: 3.10
Classifier: Programming Language :: Python :: Implementation :: CPython
Classifier: Topic :: Utilities
Requires-Python: >=3.7
License-File: LICENSE
License-File: AUTHORS.rst
Requires-Dist: matplotlib (>=3.4.2)
Requires-Dist: scikit-learn (>=0.24.2)
Requires-Dist: numpy (>=1.20.3)
Requires-Dist: pillow (>=8.0.1)
Requires-Dist: kneed (>=0.8.1)
Provides-Extra: all
Requires-Dist: black ; extra == 'all'
Requires-Dist: requests ; extra == 'all'
Requires-Dist: tox ; extra == 'all'
Requires-Dist: streamlit ; extra == 'all'
Requires-Dist: st-annotated-text ; extra == 'all'
Provides-Extra: dev
Requires-Dist: black ; extra == 'dev'
Requires-Dist: requests ; extra == 'dev'
Requires-Dist: tox ; extra == 'dev'
Provides-Extra: streamlit
Requires-Dist: streamlit ; extra == 'streamlit'
Requires-Dist: st-annotated-text ; extra == 'streamlit'
